ninput/__init__.py
ninput/ninput.py
ninput-0.3.1.dist-info/LICENSE
ninput-0.3.1.dist-info/METADATA
ninput-0.3.1.dist-info/WHEEL
ninput-0.3.1.dist-info/top_level.txt
ninput-0.3.1.dist-info/RECORD
