Metadata-Version: 2.1
Name: ninput
Version: 0.3.1
Summary: Gives option to input numbers easier
Home-page: https://github.com/niczow/ninput
Author: Kacper Nowicz
Author-email: niczow@op.pl
License: Apache License 2.0
Platform: UNKNOWN
